invenio_cache/__init__.py
invenio_cache/_compat.py
invenio_cache/bccache.py
invenio_cache/config.py
invenio_cache/decorators.py
invenio_cache/errors.py
invenio_cache/ext.py
invenio_cache/lock.py
invenio_cache/proxies.py
invenio_cache-2.1.0.dist-info/licenses/AUTHORS.rst
invenio_cache-2.1.0.dist-info/licenses/LICENSE
invenio_cache-2.1.0.dist-info/METADATA
invenio_cache-2.1.0.dist-info/WHEEL
invenio_cache-2.1.0.dist-info/entry_points.txt
invenio_cache-2.1.0.dist-info/top_level.txt
invenio_cache-2.1.0.dist-info/RECORD
