Metadata-Version: 2.4
Name: invenio-cache
Version: 2.1.0
Summary: Cache module for Invenio.
Home-page: https://github.com/inveniosoftware/invenio-cache
Author: CERN
Author-email: info@inveniosoftware.org
License: MIT
Keywords: invenio cache
Platform: any
Classifier: Development Status :: 3 - Alpha
Requires-Python: >=3.7
License-File: LICENSE
License-File: AUTHORS.rst
Requires-Dist: Flask-Caching>=1.8.0
Requires-Dist: invenio-base<3.0.0,>=2.0.0
Provides-Extra: tests
Requires-Dist: pytest-black-ng>=0.4.0; extra == "tests"
Requires-Dist: mock>=2.0.0; extra == "tests"
Requires-Dist: redis>=2.10.5; extra == "tests"
Requires-Dist: pytest-invenio<4.0.0,>=3.0.0; extra == "tests"
Requires-Dist: pytest-mock>=1.6.0; extra == "tests"
Requires-Dist: flask-login>=0.6.3; extra == "tests"
Requires-Dist: Sphinx>=3; extra == "tests"
Dynamic: license-file
